var_inspector/__init__.py
var_inspector/var_inspector.py
var_inspector-0.1.1.dist-info/LICENSE
var_inspector-0.1.1.dist-info/METADATA
var_inspector-0.1.1.dist-info/WHEEL
var_inspector-0.1.1.dist-info/RECORD
