Metadata-Version: 2.1
Name: var-inspector
Version: 0.1.1
Summary: A package for inspecting and displaying variable information
Author: tyaso777
Author-email: 49575436+tyaso777@users.noreply.github.com
Requires-Python: >=3.11,<4.0
Classifier: Programming Language :: Python :: 3
Classifier: Programming Language :: Python :: 3.11
Classifier: Programming Language :: Python :: 3.12
Requires-Dist: pandas (>=2.2.2,<3.0.0)
